take_ngram/__init__.py
take_ngram/domain/__init__.py
take_ngram/domain/ngram.py
take_ngram/logic/__init__.py
take_ngram/logic/calculate_ngram.py
take_ngram/logic/utils.py
take_ngram/persistence/__init__.py
take_ngram/persistence/data_reader.py
take_ngram/presentation/__init__.py
take_ngram/presentation/word_cloud.py
take_ngram-0.1.1.dist-info/METADATA
take_ngram-0.1.1.dist-info/WHEEL
take_ngram-0.1.1.dist-info/top_level.txt
take_ngram-0.1.1.dist-info/RECORD
