Metadata-Version: 2.1
Name: take-ngram
Version: 0.1.1
Summary: Analysis of N-gram in a set of messages
Home-page: UNKNOWN
Author: Data & Analytics Research
Author-email: analytics.dar@take.net
Maintainer: daresearch
Maintainer-email: anaytics.dar@take.net
License: MIT License
Keywords: ngram,chatbot
Platform: UNKNOWN
Classifier: Programming Language :: Python :: 3.7
Classifier: Operating System :: OS Independent
Requires-Dist: wordcloud
Requires-Dist: nltk
Requires-Dist: matplotlib
